{
    "is_success": true,
    "code": "000000",
    "message": null,
    "data": {
        "result_file_name": "temp_765ced6a3a4c45989fea87101544a68b.jpg",
        "result_ocr_text": [
            "建安有先朗𬗫荆溪縂富機社崇福寺内右邉第三婢二面之前",
            "口",
            "六之",
            "南褁府去明縣壽𭇥社富機村武公當",
            "字褔敬用𭛁家貲銭叁拾貫許本村",
            "官貟郷長全村上下等通奸應遥後",
            "佛碑記流傳衍𡸁綉世停後者猶尼",
            "佛㐲娓柱持本詩玉首望焚否進宛後",
            "孫歌泉因州碎字",
            "論",
            "",
            "本封應保後侯武公當字福敬曰",
            "龜升卷張一八六子",
            "亲㑹武侮求安渠玄吹一盂奉祀",
            "云台三年戕次云已仲春郎榖日"
        ],
        "result_bbox": [
            [
                [
                    [
                        3534.0,
                        1282.0
                    ],
                    [
                        3654.0,
                        1277.0
                    ],
                    [
                        3786.0,
                        4290.0
                    ],
                    [
                        3666.0,
                        4295.0
                    ]
                ],
                [
                    "建安有先朗𬗫荆溪縂富機社崇福寺内右邉第三婢二面之前",
                    0.9371348023414612
                ]
            ],
            [
                [
                    [
                        3019.0,
                        280.0
                    ],
                    [
                        3283.0,
                        19.0
                    ],
                    [
                        3358.0,
                        100.0
                    ],
                    [
                        3094.0,
                        362.0
                    ]
                ],
                [
                    "口",
                    0.594584047794342
                ]
            ],
            [
                [
                    [
                        2965.0,
                        922.0
                    ],
                    [
                        2995.0,
                        901.0
                    ],
                    [
                        3163.0,
                        1161.0
                    ],
                    [
                        3133.0,
                        1182.0
                    ]
                ],
                [
                    "六之",
                    0.1937786489725113
                ]
            ],
            [
                [
                    [
                        2687.0,
                        1646.0
                    ],
                    [
                        2844.0,
                        1644.0
                    ],
                    [
                        2885.0,
                        4497.0
                    ],
                    [
                        2728.0,
                        4499.0
                    ]
                ],
                [
                    "南褁府去明縣壽𭇥社富機村武公當",
                    0.8119650483131409
                ]
            ],
            [
                [
                    [
                        2471.0,
                        1658.0
                    ],
                    [
                        2639.0,
                        1656.0
                    ],
                    [
                        2685.0,
                        4481.0
                    ],
                    [
                        2517.0,
                        4483.0
                    ]
                ],
                [
                    "字褔敬用𭛁家貲銭叁拾貫許本村",
                    0.8753514289855957
                ]
            ],
            [
                [
                    [
                        2263.0,
                        1654.0
                    ],
                    [
                        2412.0,
                        1652.0
                    ],
                    [
                        2453.0,
                        4469.0
                    ],
                    [
                        2304.0,
                        4471.0
                    ]
                ],
                [
                    "官貟郷長全村上下等通奸應遥後",
                    0.719660222530365
                ]
            ],
            [
                [
                    [
                        2039.0,
                        1630.0
                    ],
                    [
                        2207.0,
                        1627.0
                    ],
                    [
                        2253.0,
                        4465.0
                    ],
                    [
                        2085.0,
                        4467.0
                    ]
                ],
                [
                    "佛碑記流傳衍𡸁綉世停後者猶尼",
                    0.727843701839447
                ]
            ],
            [
                [
                    [
                        1821.0,
                        1246.0
                    ],
                    [
                        2077.0,
                        1248.0
                    ],
                    [
                        2043.0,
                        4491.0
                    ],
                    [
                        1787.0,
                        4489.0
                    ]
                ],
                [
                    "佛㐲娓柱持本詩玉首望焚否進宛後",
                    0.7193533182144165
                ]
            ],
            [
                [
                    [
                        1632.0,
                        1621.0
                    ],
                    [
                        1792.0,
                        1620.0
                    ],
                    [
                        1800.0,
                        2970.0
                    ],
                    [
                        1640.0,
                        2971.0
                    ]
                ],
                [
                    "孫歌泉因州碎字",
                    0.6233941912651062
                ]
            ],
            [
                [
                    [
                        1444.0,
                        1825.0
                    ],
                    [
                        1572.0,
                        1825.0
                    ],
                    [
                        1572.0,
                        2010.0
                    ],
                    [
                        1444.0,
                        2010.0
                    ]
                ],
                [
                    "",
                    0.0
                ]
            ],
            [
                [
                    [
                        1312.0,
                        1258.0
                    ],
                    [
                        1688.0,
                        1258.0
                    ],
                    [
                        1688.0,
                        1548.0
                    ],
                    [
                        1312.0,
                        1548.0
                    ]
                ],
                [
                    "論",
                    0.14593078196048737
                ]
            ],
            [
                [
                    [
                        1244.0,
                        1809.0
                    ],
                    [
                        1388.0,
                        1809.0
                    ],
                    [
                        1396.0,
                        4422.0
                    ],
                    [
                        1252.0,
                        4422.0
                    ]
                ],
                [
                    "本封應保後侯武公當字福敬曰",
                    0.8888244032859802
                ]
            ],
            [
                [
                    [
                        833.0,
                        2154.0
                    ],
                    [
                        1005.0,
                        2157.0
                    ],
                    [
                        959.0,
                        4504.0
                    ],
                    [
                        787.0,
                        4500.0
                    ]
                ],
                [
                    "亲㑹武侮求安渠玄吹一盂奉祀",
                    0.5754112005233765
                ]
            ],
            [
                [
                    [
                        828.0,
                        1202.0
                    ],
                    [
                        1260.0,
                        1202.0
                    ],
                    [
                        1260.0,
                        4543.0
                    ],
                    [
                        828.0,
                        4543.0
                    ]
                ],
                [
                    "龜升卷張一八六子",
                    0.2906332015991211
                ]
            ],
            [
                [
                    [
                        657.0,
                        1631.0
                    ],
                    [
                        813.0,
                        1635.0
                    ],
                    [
                        751.0,
                        4174.0
                    ],
                    [
                        595.0,
                        4170.0
                    ]
                ],
                [
                    "云台三年戕次云已仲春郎榖日",
                    0.6633352637290955
                ]
            ]
        ],
        "details": {
            "file_name": "",
            "details": [
                {
                    "transcription": "建安有先朗𬗫荆溪縂富機社崇福寺内右邉第三婢二面之前",
                    "points": [
                        [
                            3534,
                            1282
                        ],
                        [
                            3654,
                            1277
                        ],
                        [
                            3786,
                            4290
                        ],
                        [
                            3666,
                            4295
                        ]
                    ],
                    "difficult": false
                },
                {
                    "transcription": "口",
                    "points": [
                        [
                            3019,
                            280
                        ],
                        [
                            3283,
                            19
                        ],
                        [
                            3358,
                            100
                        ],
                        [
                            3094,
                            362
                        ]
                    ],
                    "difficult": false
                },
                {
                    "transcription": "六之",
                    "points": [
                        [
                            2965,
                            922
                        ],
                        [
                            2995,
                            901
                        ],
                        [
                            3163,
                            1161
                        ],
                        [
                            3133,
                            1182
                        ]
                    ],
                    "difficult": false
                },
                {
                    "transcription": "南褁府去明縣壽𭇥社富機村武公當",
                    "points": [
                        [
                            2687,
                            1646
                        ],
                        [
                            2844,
                            1644
                        ],
                        [
                            2885,
                            4497
                        ],
                        [
                            2728,
                            4499
                        ]
                    ],
                    "difficult": false
                },
                {
                    "transcription": "字褔敬用𭛁家貲銭叁拾貫許本村",
                    "points": [
                        [
                            2471,
                            1658
                        ],
                        [
                            2639,
                            1656
                        ],
                        [
                            2685,
                            4481
                        ],
                        [
                            2517,
                            4483
                        ]
                    ],
                    "difficult": false
                },
                {
                    "transcription": "官貟郷長全村上下等通奸應遥後",
                    "points": [
                        [
                            2263,
                            1654
                        ],
                        [
                            2412,
                            1652
                        ],
                        [
                            2453,
                            4469
                        ],
                        [
                            2304,
                            4471
                        ]
                    ],
                    "difficult": false
                },
                {
                    "transcription": "佛碑記流傳衍𡸁綉世停後者猶尼",
                    "points": [
                        [
                            2039,
                            1630
                        ],
                        [
                            2207,
                            1627
                        ],
                        [
                            2253,
                            4465
                        ],
                        [
                            2085,
                            4467
                        ]
                    ],
                    "difficult": false
                },
                {
                    "transcription": "佛㐲娓柱持本詩玉首望焚否進宛後",
                    "points": [
                        [
                            1821,
                            1246
                        ],
                        [
                            2077,
                            1248
                        ],
                        [
                            2043,
                            4491
                        ],
                        [
                            1787,
                            4489
                        ]
                    ],
                    "difficult": false
                },
                {
                    "transcription": "孫歌泉因州碎字",
                    "points": [
                        [
                            1632,
                            1621
                        ],
                        [
                            1792,
                            1620
                        ],
                        [
                            1800,
                            2970
                        ],
                        [
                            1640,
                            2971
                        ]
                    ],
                    "difficult": false
                },
                {
                    "transcription": "",
                    "points": [
                        [
                            1444,
                            1825
                        ],
                        [
                            1572,
                            1825
                        ],
                        [
                            1572,
                            2010
                        ],
                        [
                            1444,
                            2010
                        ]
                    ],
                    "difficult": false
                },
                {
                    "transcription": "論",
                    "points": [
                        [
                            1312,
                            1258
                        ],
                        [
                            1688,
                            1258
                        ],
                        [
                            1688,
                            1548
                        ],
                        [
                            1312,
                            1548
                        ]
                    ],
                    "difficult": false
                },
                {
                    "transcription": "本封應保後侯武公當字福敬曰",
                    "points": [
                        [
                            1244,
                            1809
                        ],
                        [
                            1388,
                            1809
                        ],
                        [
                            1396,
                            4422
                        ],
                        [
                            1252,
                            4422
                        ]
                    ],
                    "difficult": false
                },
                {
                    "transcription": "亲㑹武侮求安渠玄吹一盂奉祀",
                    "points": [
                        [
                            833,
                            2154
                        ],
                        [
                            1005,
                            2157
                        ],
                        [
                            959,
                            4504
                        ],
                        [
                            787,
                            4500
                        ]
                    ],
                    "difficult": false
                },
                {
                    "transcription": "龜升卷張一八六子",
                    "points": [
                        [
                            828,
                            1202
                        ],
                        [
                            1260,
                            1202
                        ],
                        [
                            1260,
                            4543
                        ],
                        [
                            828,
                            4543
                        ]
                    ],
                    "difficult": false
                },
                {
                    "transcription": "云台三年戕次云已仲春郎榖日",
                    "points": [
                        [
                            657,
                            1631
                        ],
                        [
                            813,
                            1635
                        ],
                        [
                            751,
                            4174
                        ],
                        [
                            595,
                            4170
                        ]
                    ],
                    "difficult": false
                }
            ]
        }
    }
}