{
    "is_success": true,
    "code": "000000",
    "message": null,
    "data": {
        "result_file_name": "temp_1a2d4b8f57e94c8e9946acf6d6184e2f.jpg",
        "result_ocr_text": [
            "字",
            "建安省先朗𬗫涇凉縂開蒲社𠅘内右邉第二𥓓",
            "亥",
            "南策府先明縣蘭浦社仝上卞等爲立𥓓記事縁修",
            "理亭字支費銭文難於𭣣補兹喜見社內人阬天玊",
            "號慈安應出家貲史銭叁拾五貫以供支費本社推",
            "洲",
            "保爲後神再寄土園一所以供萬代血食又應出",
            "錢文十五貫寄為良夫裴公字早遇",
            "正和二年𡻕次辛酉二月十一",
            "四",
            "二",
            "拱寫社正裴世顕社胥罘有義鄉老",
            "綸",
            "果德茂阮文巨阮文禮梁文武裴文萬阮文森鿄文",
            "辛",
            "榜鿄文振罘文鯨梁文擁隱鄉長裘明海果文欣",
            "𭩮文省鿄文序𭩮文終𭩮公進𭩮登第𭩮文庶𭩮為",
            "𭩮文尼𭩮文治𭩮文体官員阮文𭭕阮文牌号",
            "范文藏鿄文娄梁文坎阮文歆玩文買鿄登魁鿄酉"
        ],
        "result_bbox": [
            [
                [
                    [
                        3506.0,
                        1274.0
                    ],
                    [
                        3650.0,
                        1271.0
                    ],
                    [
                        3709.0,
                        3852.0
                    ],
                    [
                        3566.0,
                        3855.0
                    ]
                ],
                [
                    "建安省先朗𬗫涇凉縂開蒲社𠅘内右邉第二𥓓",
                    0.9238911867141724
                ]
            ],
            [
                [
                    [
                        3351.0,
                        767.0
                    ],
                    [
                        3754.0,
                        390.0
                    ],
                    [
                        3839.0,
                        517.0
                    ],
                    [
                        3467.0,
                        894.0
                    ]
                ],
                [
                    "字",
                    0.15033040940761566
                ]
            ],
            [
                [
                    [
                        3062.0,
                        1002.0
                    ],
                    [
                        3248.0,
                        997.0
                    ],
                    [
                        3392.0,
                        6228.0
                    ],
                    [
                        3206.0,
                        6233.0
                    ]
                ],
                [
                    "南策府先明縣蘭浦社仝上卞等爲立𥓓記事縁修",
                    0.8921934962272644
                ]
            ],
            [
                [
                    [
                        3012.0,
                        271.0
                    ],
                    [
                        3295.0,
                        19.0
                    ],
                    [
                        3364.0,
                        100.0
                    ],
                    [
                        3081.0,
                        352.0
                    ]
                ],
                [
                    "亥",
                    0.12775146961212158
                ]
            ],
            [
                [
                    [
                        2796.0,
                        1008.0
                    ],
                    [
                        2992.0,
                        1002.0
                    ],
                    [
                        3168.0,
                        6227.0
                    ],
                    [
                        2972.0,
                        6233.0
                    ]
                ],
                [
                    "理亭字支費銭文難於𭣣補兹喜見社內人阬天玊",
                    0.8110561370849609
                ]
            ],
            [
                [
                    [
                        2540.0,
                        997.0
                    ],
                    [
                        2741.0,
                        992.0
                    ],
                    [
                        2896.0,
                        6253.0
                    ],
                    [
                        2695.0,
                        6259.0
                    ]
                ],
                [
                    "號慈安應出家貲史銭叁拾五貫以供支費本社推",
                    0.9676859974861145
                ]
            ],
            [
                [
                    [
                        2285.0,
                        982.0
                    ],
                    [
                        2502.0,
                        977.0
                    ],
                    [
                        2630.0,
                        6285.0
                    ],
                    [
                        2413.0,
                        6290.0
                    ]
                ],
                [
                    "保爲後神再寄土園一所以供萬代血食又應出",
                    0.9703414440155029
                ]
            ],
            [
                [
                    [
                        2276.0,
                        411.0
                    ],
                    [
                        2571.0,
                        411.0
                    ],
                    [
                        2571.0,
                        791.0
                    ],
                    [
                        2276.0,
                        791.0
                    ]
                ],
                [
                    "洲",
                    0.481810063123703
                ]
            ],
            [
                [
                    [
                        2035.0,
                        992.0
                    ],
                    [
                        2257.0,
                        987.0
                    ],
                    [
                        2343.0,
                        4939.0
                    ],
                    [
                        2121.0,
                        4944.0
                    ]
                ],
                [
                    "錢文十五貫寄為良夫裴公字早遇",
                    0.9577071070671082
                ]
            ],
            [
                [
                    [
                        1953.0,
                        4970.0
                    ],
                    [
                        2028.0,
                        4970.0
                    ],
                    [
                        2028.0,
                        5081.0
                    ],
                    [
                        1953.0,
                        5081.0
                    ]
                ],
                [
                    "綸",
                    0.2084936946630478
                ]
            ],
            [
                [
                    [
                        1869.0,
                        4170.0
                    ],
                    [
                        2002.0,
                        4170.0
                    ],
                    [
                        2002.0,
                        4365.0
                    ],
                    [
                        1869.0,
                        4365.0
                    ]
                ],
                [
                    "四",
                    0.2688652276992798
                ]
            ],
            [
                [
                    [
                        1774.0,
                        1017.0
                    ],
                    [
                        1975.0,
                        1013.0
                    ],
                    [
                        2045.0,
                        4119.0
                    ],
                    [
                        1844.0,
                        4124.0
                    ]
                ],
                [
                    "正和二年𡻕次辛酉二月十一",
                    0.9777114987373352
                ]
            ],
            [
                [
                    [
                        1539.0,
                        2311.0
                    ],
                    [
                        1756.0,
                        2308.0
                    ],
                    [
                        1815.0,
                        6291.0
                    ],
                    [
                        1599.0,
                        6294.0
                    ]
                ],
                [
                    "拱寫社正裴世顕社胥罘有義鄉老",
                    0.9264280200004578
                ]
            ],
            [
                [
                    [
                        1483.0,
                        354.0
                    ],
                    [
                        2034.0,
                        354.0
                    ],
                    [
                        2034.0,
                        847.0
                    ],
                    [
                        1483.0,
                        847.0
                    ]
                ],
                [
                    "二",
                    0.10655559599399567
                ]
            ],
            [
                [
                    [
                        1273.0,
                        1027.0
                    ],
                    [
                        1490.0,
                        1024.0
                    ],
                    [
                        1565.0,
                        6286.0
                    ],
                    [
                        1348.0,
                        6289.0
                    ]
                ],
                [
                    "果德茂阮文巨阮文禮梁文武裴文萬阮文森鿄文",
                    0.9276668429374695
                ]
            ],
            [
                [
                    [
                        1018.0,
                        1000.0
                    ],
                    [
                        1235.0,
                        998.0
                    ],
                    [
                        1299.0,
                        6276.0
                    ],
                    [
                        1082.0,
                        6279.0
                    ]
                ],
                [
                    "榜鿄文振罘文鯨梁文擁隱鄉長裘明海果文欣",
                    0.7531671524047852
                ]
            ],
            [
                [
                    [
                        867.0,
                        430.0
                    ],
                    [
                        1354.0,
                        413.0
                    ],
                    [
                        1369.0,
                        839.0
                    ],
                    [
                        881.0,
                        856.0
                    ]
                ],
                [
                    "辛",
                    0.09812349081039429
                ]
            ],
            [
                [
                    [
                        778.0,
                        999.0
                    ],
                    [
                        985.0,
                        999.0
                    ],
                    [
                        995.0,
                        6293.0
                    ],
                    [
                        789.0,
                        6293.0
                    ]
                ],
                [
                    "𭩮文省鿄文序𭩮文終𭩮公進𭩮登第𭩮文庶𭩮為",
                    0.8683080673217773
                ]
            ],
            [
                [
                    [
                        513.0,
                        1014.0
                    ],
                    [
                        735.0,
                        1015.0
                    ],
                    [
                        719.0,
                        6232.0
                    ],
                    [
                        497.0,
                        6231.0
                    ]
                ],
                [
                    "𭩮文尼𭩮文治𭩮文体官員阮文𭭕阮文牌号",
                    0.8943512439727783
                ]
            ],
            [
                [
                    [
                        262.0,
                        1009.0
                    ],
                    [
                        479.0,
                        1010.0
                    ],
                    [
                        452.0,
                        6350.0
                    ],
                    [
                        236.0,
                        6349.0
                    ]
                ],
                [
                    "范文藏鿄文娄梁文坎阮文歆玩文買鿄登魁鿄酉",
                    0.8537499308586121
                ]
            ]
        ],
        "details": {
            "file_name": "",
            "details": [
                {
                    "transcription": "建安省先朗𬗫涇凉縂開蒲社𠅘内右邉第二𥓓",
                    "points": [
                        [
                            3506,
                            1274
                        ],
                        [
                            3650,
                            1271
                        ],
                        [
                            3709,
                            3852
                        ],
                        [
                            3566,
                            3855
                        ]
                    ],
                    "difficult": false
                },
                {
                    "transcription": "字",
                    "points": [
                        [
                            3351,
                            767
                        ],
                        [
                            3754,
                            390
                        ],
                        [
                            3839,
                            517
                        ],
                        [
                            3467,
                            894
                        ]
                    ],
                    "difficult": false
                },
                {
                    "transcription": "南策府先明縣蘭浦社仝上卞等爲立𥓓記事縁修",
                    "points": [
                        [
                            3062,
                            1002
                        ],
                        [
                            3248,
                            997
                        ],
                        [
                            3392,
                            6228
                        ],
                        [
                            3206,
                            6233
                        ]
                    ],
                    "difficult": false
                },
                {
                    "transcription": "亥",
                    "points": [
                        [
                            3012,
                            271
                        ],
                        [
                            3295,
                            19
                        ],
                        [
                            3364,
                            100
                        ],
                        [
                            3081,
                            352
                        ]
                    ],
                    "difficult": false
                },
                {
                    "transcription": "理亭字支費銭文難於𭣣補兹喜見社內人阬天玊",
                    "points": [
                        [
                            2796,
                            1008
                        ],
                        [
                            2992,
                            1002
                        ],
                        [
                            3168,
                            6227
                        ],
                        [
                            2972,
                            6233
                        ]
                    ],
                    "difficult": false
                },
                {
                    "transcription": "號慈安應出家貲史銭叁拾五貫以供支費本社推",
                    "points": [
                        [
                            2540,
                            997
                        ],
                        [
                            2741,
                            992
                        ],
                        [
                            2896,
                            6253
                        ],
                        [
                            2695,
                            6259
                        ]
                    ],
                    "difficult": false
                },
                {
                    "transcription": "保爲後神再寄土園一所以供萬代血食又應出",
                    "points": [
                        [
                            2285,
                            982
                        ],
                        [
                            2502,
                            977
                        ],
                        [
                            2630,
                            6285
                        ],
                        [
                            2413,
                            6290
                        ]
                    ],
                    "difficult": false
                },
                {
                    "transcription": "洲",
                    "points": [
                        [
                            2276,
                            411
                        ],
                        [
                            2571,
                            411
                        ],
                        [
                            2571,
                            791
                        ],
                        [
                            2276,
                            791
                        ]
                    ],
                    "difficult": false
                },
                {
                    "transcription": "錢文十五貫寄為良夫裴公字早遇",
                    "points": [
                        [
                            2035,
                            992
                        ],
                        [
                            2257,
                            987
                        ],
                        [
                            2343,
                            4939
                        ],
                        [
                            2121,
                            4944
                        ]
                    ],
                    "difficult": false
                },
                {
                    "transcription": "綸",
                    "points": [
                        [
                            1953,
                            4970
                        ],
                        [
                            2028,
                            4970
                        ],
                        [
                            2028,
                            5081
                        ],
                        [
                            1953,
                            5081
                        ]
                    ],
                    "difficult": false
                },
                {
                    "transcription": "四",
                    "points": [
                        [
                            1869,
                            4170
                        ],
                        [
                            2002,
                            4170
                        ],
                        [
                            2002,
                            4365
                        ],
                        [
                            1869,
                            4365
                        ]
                    ],
                    "difficult": false
                },
                {
                    "transcription": "正和二年𡻕次辛酉二月十一",
                    "points": [
                        [
                            1774,
                            1017
                        ],
                        [
                            1975,
                            1013
                        ],
                        [
                            2045,
                            4119
                        ],
                        [
                            1844,
                            4124
                        ]
                    ],
                    "difficult": false
                },
                {
                    "transcription": "拱寫社正裴世顕社胥罘有義鄉老",
                    "points": [
                        [
                            1539,
                            2311
                        ],
                        [
                            1756,
                            2308
                        ],
                        [
                            1815,
                            6291
                        ],
                        [
                            1599,
                            6294
                        ]
                    ],
                    "difficult": false
                },
                {
                    "transcription": "二",
                    "points": [
                        [
                            1483,
                            354
                        ],
                        [
                            2034,
                            354
                        ],
                        [
                            2034,
                            847
                        ],
                        [
                            1483,
                            847
                        ]
                    ],
                    "difficult": false
                },
                {
                    "transcription": "果德茂阮文巨阮文禮梁文武裴文萬阮文森鿄文",
                    "points": [
                        [
                            1273,
                            1027
                        ],
                        [
                            1490,
                            1024
                        ],
                        [
                            1565,
                            6286
                        ],
                        [
                            1348,
                            6289
                        ]
                    ],
                    "difficult": false
                },
                {
                    "transcription": "榜鿄文振罘文鯨梁文擁隱鄉長裘明海果文欣",
                    "points": [
                        [
                            1018,
                            1000
                        ],
                        [
                            1235,
                            998
                        ],
                        [
                            1299,
                            6276
                        ],
                        [
                            1082,
                            6279
                        ]
                    ],
                    "difficult": false
                },
                {
                    "transcription": "辛",
                    "points": [
                        [
                            867,
                            430
                        ],
                        [
                            1354,
                            413
                        ],
                        [
                            1369,
                            839
                        ],
                        [
                            881,
                            856
                        ]
                    ],
                    "difficult": false
                },
                {
                    "transcription": "𭩮文省鿄文序𭩮文終𭩮公進𭩮登第𭩮文庶𭩮為",
                    "points": [
                        [
                            778,
                            999
                        ],
                        [
                            985,
                            999
                        ],
                        [
                            995,
                            6293
                        ],
                        [
                            789,
                            6293
                        ]
                    ],
                    "difficult": false
                },
                {
                    "transcription": "𭩮文尼𭩮文治𭩮文体官員阮文𭭕阮文牌号",
                    "points": [
                        [
                            513,
                            1014
                        ],
                        [
                            735,
                            1015
                        ],
                        [
                            719,
                            6232
                        ],
                        [
                            497,
                            6231
                        ]
                    ],
                    "difficult": false
                },
                {
                    "transcription": "范文藏鿄文娄梁文坎阮文歆玩文買鿄登魁鿄酉",
                    "points": [
                        [
                            262,
                            1009
                        ],
                        [
                            479,
                            1010
                        ],
                        [
                            452,
                            6350
                        ],
                        [
                            236,
                            6349
                        ]
                    ],
                    "difficult": false
                }
            ]
        }
    }
}